sgf.py
sgf-0.5.dist-info/DESCRIPTION.rst
sgf-0.5.dist-info/METADATA
sgf-0.5.dist-info/metadata.json
sgf-0.5.dist-info/RECORD
sgf-0.5.dist-info/top_level.txt
sgf-0.5.dist-info/WHEEL
