Metadata-Version: 2.0
Name: sgf
Version: 0.5
Summary: Python library for reading and writing Smart Game Format
Home-page: http://github.com/jtauber/sgf
Author: James Tauber
Author-email: jtauber@jtauber.com
License: MIT
Platform: UNKNOWN
Classifier: Development Status :: 4 - Beta
Classifier: License :: OSI Approved :: MIT License
Classifier: Programming Language :: Python :: 2.7
Classifier: Topic :: Games/Entertainment :: Board Games
Classifier: Topic :: Utilities
